protobuilder/__init__.py
protobuilder/build.py
kody_protobuilder-0.0.4.dist-info/METADATA
kody_protobuilder-0.0.4.dist-info/WHEEL
kody_protobuilder-0.0.4.dist-info/top_level.txt
kody_protobuilder-0.0.4.dist-info/RECORD
